ewmh_m2m/__init__.py
ewmh_m2m/__main__.py
ewmh_m2m/_version.py
ewmh_m2m/geometry.py
ewmh_m2m/ordinal.py
ewmh_m2m/screen.py
ewmh_m2m/window.py
ewmh_m2m-2.1.1.dist-info/METADATA
ewmh_m2m-2.1.1.dist-info/WHEEL
ewmh_m2m-2.1.1.dist-info/entry_points.txt
ewmh_m2m-2.1.1.dist-info/licenses/AUTHORS.rst
ewmh_m2m-2.1.1.dist-info/licenses/LICENSE.txt
ewmh_m2m-2.1.1.dist-info/RECORD
