Metadata-Version: 2.3
Name: ewmh_m2m
Version: 2.1.1
Summary: Move window between monitor in EWMH compliant WM
Project-URL: Documentation, https://ewmh-m2m.readthedocs.io
Project-URL: Repository, https://github.com/AlexisBRENON/ewmh_m2m
Author-email: Alexis BRENON <brenon.alexis@gmail.com>
License: The MIT License (MIT)
License-File: AUTHORS.rst
License-File: LICENSE.txt
Classifier: Development Status :: 5 - Production/Stable
Classifier: License :: OSI Approved :: MIT License
Classifier: Programming Language :: Python :: 3
Requires-Python: >=3.8
Requires-Dist: xcffib==0.8.1
Requires-Dist: xpybutil==0.0.6
Provides-Extra: docs
Requires-Dist: sphinx~=7.4; extra == 'docs'
Provides-Extra: testing
Requires-Dist: pytest; extra == 'testing'
Requires-Dist: pytest-cov; extra == 'testing'
